ranges/Range.py
ranges/RangeDict.py
ranges/RangeSet.py
ranges/__init__.py
ranges/_helper.py
test/__init__.py
test/test_Range.py
test/test_RangeDict.py
test/test_RangeSet.py
test/test_base.py
test/test_issues.py
python_ranges-1.2.1.dist-info/LICENSE.txt
python_ranges-1.2.1.dist-info/METADATA
python_ranges-1.2.1.dist-info/WHEEL
python_ranges-1.2.1.dist-info/top_level.txt
python_ranges-1.2.1.dist-info/RECORD
