Metadata-Version: 2.1
Name: python-ranges
Version: 1.2.1
Summary: Continuous Range, RangeSet, and RangeDict data structures
Home-page: https://github.com/superbird11/ranges
Author: Louis Jacobowitz
Author-email: ldjacobowitzer@gmail.com
License: UNKNOWN
Project-URL: Documentation, https://python-ranges.readthedocs.io/en/latest/
Project-URL: GitHub, https://github.com/Superbird11/ranges
Platform: UNKNOWN
Classifier: Programming Language :: Python :: 3
Classifier: License :: OSI Approved :: MIT License
Classifier: Operating System :: OS Independent
Requires-Python: >=3.9
License-File: LICENSE.txt
